analyticViz/__init__.py
analyticViz/viz.py
analyticViz-0.0.1.dist-info/LICENSE.txt
analyticViz-0.0.1.dist-info/METADATA
analyticViz-0.0.1.dist-info/WHEEL
analyticViz-0.0.1.dist-info/top_level.txt
analyticViz-0.0.1.dist-info/RECORD
