Metadata-Version: 2.1
Name: analyticViz
Version: 0.0.1
Summary: Package for data visualization
Home-page: UNKNOWN
Author: David Adarkwah
Author-email: davidwyse48@gmail.com
License: UNKNOWN
Keywords: plotly,analysis,visualization,data analysis,data science
Platform: UNKNOWN
Classifier: Programming Language :: Python :: 3
Classifier: License :: OSI Approved :: MIT License
Classifier: Operating System :: OS Independent
Requires-Python: >=3.6
License-File: LICENSE.txt
